ADmanage/__init__.py
ADmanage/libs/__init__.py
ADmanage/libs/impacket/__init__.py
ADmanage/libs/impacket/structure.py
ADmanage-0.9.dist-info/METADATA
ADmanage-0.9.dist-info/WHEEL
ADmanage-0.9.dist-info/top_level.txt
ADmanage-0.9.dist-info/RECORD
