Metadata-Version: 2.1
Name: ADmanage
Version: 0.9
Requires-Dist: ldap3
Requires-Dist: six
Requires-Dist: dnspython
Requires-Dist: pycryptodome
